<?xml version="1.0" encoding="UTF-8"?>
<handler-plugins xmlns="http://com.messagebus">
    <produce>
        <handler>
            <handler-name>Validate-Handler</handler-name>
            <handler-path>com.messagebus.client.handler.produce.ProduceParamValidator</handler-path>
        </handler>
        <handler>
            <handler-name>Message-Body-Size</handler-name>
            <handler-path>com.messagebus.client.handler.common.MessageBodySizeLimiter</handler-path>
        </handler>
        <handler>
            <handler-name>Produce-Permission-Checker</handler-name>
            <handler-path>com.messagebus.client.handler.produce.ProducePermission</handler-path>
        </handler>
        <handler>
            <handler-name>MessageId-Generator</handler-name>
            <handler-path>com.messagebus.client.handler.common.MessageIdGenerator</handler-path>
        </handler>
        <handler>
            <handler-name>Real-Produce</handler-name>
            <handler-path>com.messagebus.client.handler.produce.RealProduce</handler-path>
        </handler>
    </produce>
    <consumer>
        <handler>
            <handler-name>Validate-Handler</handler-name>
            <handler-path>com.messagebus.client.handler.consume.ConsumeParamValidator</handler-path>
        </handler>
        <handler>
            <handler-name>Consume-Permission-Checker</handler-name>
            <handler-path>com.messagebus.client.handler.consume.ConsumePermission</handler-path>
        </handler>
        <handler>
            <handler-name>Consumer-Tag-Generator</handler-name>
            <handler-path>com.messagebus.client.handler.consume.ConsumerTagGenerator</handler-path>
        </handler>
        <handler>
            <handler-name>Real-Consumer</handler-name>
            <handler-path>com.messagebus.client.handler.consume.RealConsumer</handler-path>
        </handler>
        <handler>
            <handler-name>Consume-Loop-Handler</handler-name>
            <handler-path>com.messagebus.client.handler.consume.ConsumerDispatchHandler</handler-path>
        </handler>
    </consumer>
    <request>
        <handler>
            <handler-name>Validate-Handler</handler-name>
            <handler-path>com.messagebus.client.handler.request.RequestParamValidator</handler-path>
        </handler>
        <handler>
            <handler-name>Message-Body-Size</handler-name>
            <handler-path>com.messagebus.client.handler.common.MessageBodySizeLimiter</handler-path>
        </handler>
        <handler>
            <handler-name>Request-Permission-Checker</handler-name>
            <handler-path>com.messagebus.client.handler.request.RequestPermission</handler-path>
        </handler>
        <handler>
            <handler-name>MessageId-Generator</handler-name>
            <handler-path>com.messagebus.client.handler.common.MessageIdGenerator</handler-path>
        </handler>
        <handler>
            <handler-name>Temp-Queue-Initializer</handler-name>
            <handler-path>com.messagebus.client.handler.request.TempQueueInitializer</handler-path>
        </handler>
        <handler>
            <handler-name>Real-Requester</handler-name>
            <handler-path>com.messagebus.client.handler.request.RealRequester</handler-path>
        </handler>
        <handler>
            <handler-name>Consumer-Tag-Generator</handler-name>
            <handler-path>com.messagebus.client.handler.consume.ConsumerTagGenerator</handler-path>
        </handler>
        <handler>
            <handler-name>Blocked-And-Timeout-Response</handler-name>
            <handler-path>com.messagebus.client.handler.request.BlockedAndTimeoutResponser</handler-path>
        </handler>
    </request>
    <response>
        <handler>
            <handler-name>Consumer-Tag-Generator</handler-name>
            <handler-path>com.messagebus.client.handler.consume.ConsumerTagGenerator</handler-path>
        </handler>
        <handler>
            <handler-name>Validate-Handler</handler-name>
            <handler-path>com.messagebus.client.handler.response.ResponseParamValidator</handler-path>
        </handler>
        <handler>
            <handler-name>Response-Handler</handler-name>
            <handler-path>com.messagebus.client.handler.response.ResponsePermission</handler-path>
        </handler>
        <handler>
            <handler-name>Real-Consumer</handler-name>
            <handler-path>com.messagebus.client.handler.consume.RealConsumer</handler-path>
        </handler>
        <handler>
            <handler-name>Response-Loop-Handler</handler-name>
            <handler-path>com.messagebus.client.handler.response.ResponseLoopHandler</handler-path>
        </handler>
        <!--<handler>-->
        <!--<handler-name>MessageId-Generator</handler-name>-->
        <!--<handler-path>com.messagebus.client.handler.common.MessageIdGenerator</handler-path>-->
        <!--</handler>-->
        <!--<handler>-->
        <!--<handler-name>Validate-Handler</handler-name>-->
        <!--<handler-path>com.messagebus.client.handler.response.ResponseParamValidator</handler-path>-->
        <!--</handler>-->
        <!--<handler>-->
        <!--<handler-name>Response-Sender</handler-name>-->
        <!--<handler-path>com.messagebus.client.handler.response.ResponseSender</handler-path>-->
        <!--</handler>-->
    </response>
    <publish>
        <handler>
            <handler-name>MessageId-Generator</handler-name>
            <handler-path>com.messagebus.client.handler.common.MessageIdGenerator</handler-path>
        </handler>
        <handler>
            <handler-name>Validate-Handler</handler-name>
            <handler-path>com.messagebus.client.handler.publish.PublishParamValidator</handler-path>
        </handler>
        <handler>
            <handler-name>Publish-Permission</handler-name>
            <handler-path>com.messagebus.client.handler.publish.PublishPermission</handler-path>
        </handler>
        <handler>
            <handler-name>Publish-Filter</handler-name>
            <handler-path>com.messagebus.client.handler.publish.PublishFilter</handler-path>
        </handler>
        <handler>
            <handler-name>Real-Publish</handler-name>
            <handler-path>com.messagebus.client.handler.publish.RealPublisher</handler-path>
        </handler>
    </publish>
    <subscribe>
        <handler>
            <handler-name>Consumer-Tag-Generator</handler-name>
            <handler-path>com.messagebus.client.handler.consume.ConsumerTagGenerator</handler-path>
        </handler>
        <handler>
            <handler-name>Validate-Handler</handler-name>
            <handler-path>com.messagebus.client.handler.subscribe.SubscribeParamValidator</handler-path>
        </handler>
        <handler>
            <handler-name>Subscribe-Permission</handler-name>
            <handler-path>com.messagebus.client.handler.subscribe.SubscribePermission</handler-path>
        </handler>
        <handler>
            <handler-name>Real-Consumer</handler-name>
            <handler-path>com.messagebus.client.handler.consume.RealConsumer</handler-path>
        </handler>
        <handler>
            <handler-name>Subscribe-Loop-Handler</handler-name>
            <handler-path>com.messagebus.client.handler.subscribe.SubscribeLoopHandler</handler-path>
        </handler>
    </subscribe>
    <broadcast>
        <handler>
            <handler-name>MessageId-Generator</handler-name>
            <handler-path>com.messagebus.client.handler.common.MessageIdGenerator</handler-path>
        </handler>
        <handler>
            <handler-name>Validate-Handler</handler-name>
            <handler-path>com.messagebus.client.handler.broadcast.BroadcastParamValidator</handler-path>
        </handler>
        <handler>
            <handler-name>Real-Broadcaster</handler-name>
            <handler-path>com.messagebus.client.handler.broadcast.RealBroadcaster</handler-path>
        </handler>
    </broadcast>
</handler-plugins>